pip_resolved/__init__.py
pip_resolved/__main__.py
pip_resolved/main.py
pip_resolved-0.3.0.dist-info/entry_points.txt
pip_resolved-0.3.0.dist-info/WHEEL
pip_resolved-0.3.0.dist-info/METADATA
pip_resolved-0.3.0.dist-info/RECORD
