Metadata-Version: 2.1
Name: pip-resolved
Version: 0.3.0
Summary: Install wheels with pre-resolved dependencies
License: MIT
Author-email: Lucas Cardozo <lucasecardozo@gmail.com>
Requires-Python: >=3.7
